__init__.py
AnotherSpace/__init__.py
AnotherSpace/Config/__init__.py
AnotherSpace/Encrypter/__init__.py
AnotherSpace/Logger/__init__.py
AnotherSpace/Validator/__init__.py
AnotherSpace-0.0.5.dist-info/LICENCE
AnotherSpace-0.0.5.dist-info/METADATA
AnotherSpace-0.0.5.dist-info/WHEEL
AnotherSpace-0.0.5.dist-info/top_level.txt
AnotherSpace-0.0.5.dist-info/RECORD
